AUTHORS
LICENCE
MANIFEST.in
README.md
requirements.txt
setup.py
Ruaumoko.egg-info/PKG-INFO
Ruaumoko.egg-info/SOURCES.txt
Ruaumoko.egg-info/dependency_links.txt
Ruaumoko.egg-info/entry_points.txt
Ruaumoko.egg-info/requires.txt
Ruaumoko.egg-info/top_level.txt
deploy/api.wsgi
deploy/uwsgi.yaml.dist
ruaumoko/__init__.py
ruaumoko/_compat.py
ruaumoko/api.py
ruaumoko/asciiart.py
ruaumoko/dataset.c
ruaumoko/dataset.pyx
ruaumoko/download.py
ruaumoko/get_cmd.py
ruaumoko/manager.py