Metadata-Version: 1.1
Name: Ruaumoko
Version: 0.2.0
Summary: Ground Elevation API
Home-page: http://www.cusf.co.uk/wiki/ruaumoko
Author: Cambridge University Spaceflight
Author-email: contact@cusf.co.uk
License: GPLv3+
Platform: UNKNOWN
Classifier: Development Status :: 4 - Beta
Classifier: Intended Audience :: Science/Research
Classifier: License :: OSI Approved :: GNU General Public License v3 or later (GPLv3+)
Classifier: Programming Language :: Python :: 3.3
Classifier: Topic :: Scientific/Engineering
